<?xml version="1.0" encoding="UTF-8"?>
<playlist version="1">
<title>hwdVideoShare featured Playlist</title>
<info>http:/xspf.org/xspf-v1.html</info>
<date>2012-09-01 10:25:44</date>
<trackList>

  <track>
    <id><![CDATA[158]]></id>
    <videotitle><![CDATA[How to Play Say it Ain&#39;t So by Weezer (Lesson/Tutorial)]]></videotitle>
    <videocode><![CDATA[j3v1nGjSpRw]]></videocode>
    <videotype><![CDATA[youtube.com]]></videotype>
    <thumbnail><![CDATA[tp-158.jpg]]></thumbnail>
    <category><![CDATA[]]></category>
    <category_id><![CDATA[1]]></category_id>
    <description><![CDATA[How to Play Say it Ain&#39;t So by Weezer (Lesson/Tutorial)

For more videos by Zaheer. Please visit his profile at www.shigaru.com

One of the fastest growing communities sharing the best music tutorials on the web]]></description>
    <views><![CDATA[16]]></views>
    <views><![CDATA[16]]></views>
    <date><![CDATA[2012-08-25 16:02:48]]></date>
    <duration><![CDATA[06:06]]></duration>
    <rating><![CDATA[5.00]]></rating>
    <uploader><![CDATA[admin]]></uploader>
    <uploader_id><![CDATA[79]]></uploader_id>
    <avatar><![CDATA[79_4f25862a04afa.jpg]]></avatar>
    <comments><![CDATA[0]]></comments>
    <tags><![CDATA[How-to, weezer Play say, aint so, basic, lesson, beginner, easy, novice, amateur, starting, level, tutor, tutorial, explanation, teacher, how to play, lear]]></tags>
  </track>

  <track>
    <id><![CDATA[157]]></id>
    <videotitle><![CDATA[Los instrumentos musicales]]></videotitle>
    <videocode><![CDATA[vbqLG0S98N0]]></videocode>
    <videotype><![CDATA[youtube.com]]></videotype>
    <thumbnail><![CDATA[tp-157.jpg]]></thumbnail>
    <category><![CDATA[]]></category>
    <category_id><![CDATA[3]]></category_id>
    <description><![CDATA[Aqu&#237;  contrar&#225;s la agrupaci&#243;n general de los instrumentos musicales y de la colocaci&#243;n de &#233;stos en la orquesta&#161;&#161;Que disfruteis&#161;&#161;]]></description>
    <views><![CDATA[22]]></views>
    <views><![CDATA[22]]></views>
    <date><![CDATA[2012-07-27 18:59:59]]></date>
    <duration><![CDATA[06:14]]></duration>
    <rating><![CDATA[0.00]]></rating>
    <uploader><![CDATA[murcialito]]></uploader>
    <uploader_id><![CDATA[67]]></uploader_id>
    <avatar><![CDATA[67_4f2856bc37049.jpg]]></avatar>
    <comments><![CDATA[0]]></comments>
    <tags><![CDATA[independiente]]></tags>
  </track>

  <track>
    <id><![CDATA[155]]></id>
    <videotitle><![CDATA[Zona Norte Posse -  Rap suizida /acojonate/ (1998)]]></videotitle>
    <videocode><![CDATA[3Ucwhy7hd5I]]></videocode>
    <videotype><![CDATA[youtube.com]]></videotype>
    <thumbnail><![CDATA[tp-155.jpg]]></thumbnail>
    <category><![CDATA[]]></category>
    <category_id><![CDATA[2]]></category_id>
    <description><![CDATA[La ZNP se divid&#237;a en dos con la creaci&#243;n de la ZNP+ (Zona Norte Posse Positiva) formada por los grupos sat&#233;lites al grupo g&#233;rmen, y &#233;stos volv&#237;an a atacar con nuevas maquetas de corte m&#225;s gangster y sin pelos en la lengua. Esta cinta vi&#243; la luz en 1998 y fu&#233; grabada a modo de freestyle para demostrar y avisar a todos que, a&#250;n con notables bajas, la crew m&#225;s conocida de Alicante no hab&#237;a muerto.


Znp mc lee picolo bop m-90 rap vieja escuela hip hop JRinsanu
http://maximorespeto.blogspot.com]]></description>
    <views><![CDATA[16]]></views>
    <views><![CDATA[16]]></views>
    <date><![CDATA[2012-02-03 14:50:21]]></date>
    <duration><![CDATA[04:05]]></duration>
    <rating><![CDATA[4.00]]></rating>
    <uploader><![CDATA[admin]]></uploader>
    <uploader_id><![CDATA[79]]></uploader_id>
    <avatar><![CDATA[79_4f25862a04afa.jpg]]></avatar>
    <comments><![CDATA[1]]></comments>
    <tags><![CDATA[Znp, mc, lee, picolo, bop, m-90, rap, vieja, escuela, hip, hop, JRinsanu]]></tags>
  </track>

  <track>
    <id><![CDATA[146]]></id>
    <videotitle><![CDATA[PI&#209;ON FIJO rio, rio]]></videotitle>
    <videocode><![CDATA[odPeVUp_oq0]]></videocode>
    <videotype><![CDATA[youtube.com]]></videotype>
    <thumbnail><![CDATA[tp-146.jpg]]></thumbnail>
    <category><![CDATA[]]></category>
    <category_id><![CDATA[2]]></category_id>
    <description><![CDATA[Bajate el dvd en:
http://www.taringa.net/posts/downloads/2428954/Pi&#241;on-Fijo-Ratdvd.html]]></description>
    <views><![CDATA[27]]></views>
    <views><![CDATA[27]]></views>
    <date><![CDATA[2012-02-03 14:49:49]]></date>
    <duration><![CDATA[03:26]]></duration>
    <rating><![CDATA[0.00]]></rating>
    <uploader><![CDATA[admin]]></uploader>
    <uploader_id><![CDATA[79]]></uploader_id>
    <avatar><![CDATA[79_4f25862a04afa.jpg]]></avatar>
    <comments><![CDATA[0]]></comments>
    <tags><![CDATA[PIÑON FIJO rio, rio]]></tags>
  </track>

  <track>
    <id><![CDATA[145]]></id>
    <videotitle><![CDATA[PI&#209;ON FIJO pi&#241;on fijo es mi nombre]]></videotitle>
    <videocode><![CDATA[EkaKwa1COOo]]></videocode>
    <videotype><![CDATA[youtube.com]]></videotype>
    <thumbnail><![CDATA[tp-145.jpg]]></thumbnail>
    <category><![CDATA[]]></category>
    <category_id><![CDATA[2]]></category_id>
    <description><![CDATA[PI&#209;ON FIJO pi&#241;on fijo es mi nombre]]></description>
    <views><![CDATA[35]]></views>
    <views><![CDATA[35]]></views>
    <date><![CDATA[2012-02-03 14:49:44]]></date>
    <duration><![CDATA[01:53]]></duration>
    <rating><![CDATA[0.00]]></rating>
    <uploader><![CDATA[admin]]></uploader>
    <uploader_id><![CDATA[79]]></uploader_id>
    <avatar><![CDATA[79_4f25862a04afa.jpg]]></avatar>
    <comments><![CDATA[0]]></comments>
    <tags><![CDATA[PIÑON, FIJO, piñon, fijo, es, mi, nombre]]></tags>
  </track>

  <track>
    <id><![CDATA[144]]></id>
    <videotitle><![CDATA[con las alitas arriba, pi&#241;on fijo]]></videotitle>
    <videocode><![CDATA[huAQhNSipgo]]></videocode>
    <videotype><![CDATA[youtube.com]]></videotype>
    <thumbnail><![CDATA[tp-144.jpg]]></thumbnail>
    <category><![CDATA[]]></category>
    <category_id><![CDATA[2]]></category_id>
    <description><![CDATA[video de pi&#241;on fijo]]></description>
    <views><![CDATA[26]]></views>
    <views><![CDATA[26]]></views>
    <date><![CDATA[2012-02-03 14:49:40]]></date>
    <duration><![CDATA[02:17]]></duration>
    <rating><![CDATA[0.00]]></rating>
    <uploader><![CDATA[admin]]></uploader>
    <uploader_id><![CDATA[79]]></uploader_id>
    <avatar><![CDATA[79_4f25862a04afa.jpg]]></avatar>
    <comments><![CDATA[0]]></comments>
    <tags><![CDATA[piñon, fijo]]></tags>
  </track>

  <track>
    <id><![CDATA[143]]></id>
    <videotitle><![CDATA[gallina turuleca
      - YouTube]]></videotitle>
    <videocode><![CDATA[-kfBsoe4pkc]]></videocode>
    <videotype><![CDATA[youtube.com]]></videotype>
    <thumbnail><![CDATA[tp-143.jpg]]></thumbnail>
    <category><![CDATA[]]></category>
    <category_id><![CDATA[2]]></category_id>
    <description><![CDATA[PI&#209;ON FIJO la gallina turuleca]]></description>
    <views><![CDATA[32]]></views>
    <views><![CDATA[32]]></views>
    <date><![CDATA[2012-02-03 14:49:36]]></date>
    <duration><![CDATA[0:00:00]]></duration>
    <rating><![CDATA[0.00]]></rating>
    <uploader><![CDATA[admin]]></uploader>
    <uploader_id><![CDATA[79]]></uploader_id>
    <avatar><![CDATA[79_4f25862a04afa.jpg]]></avatar>
    <comments><![CDATA[0]]></comments>
    <tags><![CDATA[PIÑON, FIJO, la, gallina, turuleca]]></tags>
  </track>

  <track>
    <id><![CDATA[142]]></id>
    <videotitle><![CDATA[PI&#209;ON FIJO basta de mamadera]]></videotitle>
    <videocode><![CDATA[JcQJRb3DCkc]]></videocode>
    <videotype><![CDATA[youtube.com]]></videotype>
    <thumbnail><![CDATA[tp-142.jpg]]></thumbnail>
    <category><![CDATA[]]></category>
    <category_id><![CDATA[2]]></category_id>
    <description><![CDATA[PI&#209;ON FIJO basta de mamadera]]></description>
    <views><![CDATA[33]]></views>
    <views><![CDATA[33]]></views>
    <date><![CDATA[2012-02-03 14:49:32]]></date>
    <duration><![CDATA[02:55]]></duration>
    <rating><![CDATA[0.00]]></rating>
    <uploader><![CDATA[admin]]></uploader>
    <uploader_id><![CDATA[79]]></uploader_id>
    <avatar><![CDATA[79_4f25862a04afa.jpg]]></avatar>
    <comments><![CDATA[1]]></comments>
    <tags><![CDATA[PIÑON, FIJO, basta, de, mamadera]]></tags>
  </track>

  <track>
    <id><![CDATA[141]]></id>
    <videotitle><![CDATA[PI&#209;ON FIJO nene deja el chupete]]></videotitle>
    <videocode><![CDATA[Nc1BjN5VH7M]]></videocode>
    <videotype><![CDATA[youtube.com]]></videotype>
    <thumbnail><![CDATA[tp-141.jpg]]></thumbnail>
    <category><![CDATA[]]></category>
    <category_id><![CDATA[2]]></category_id>
    <description><![CDATA[PI&#209;ON FIJO nene deja el chupete]]></description>
    <views><![CDATA[35]]></views>
    <views><![CDATA[35]]></views>
    <date><![CDATA[2012-02-03 14:49:27]]></date>
    <duration><![CDATA[04:08]]></duration>
    <rating><![CDATA[0.00]]></rating>
    <uploader><![CDATA[admin]]></uploader>
    <uploader_id><![CDATA[79]]></uploader_id>
    <avatar><![CDATA[79_4f25862a04afa.jpg]]></avatar>
    <comments><![CDATA[1]]></comments>
    <tags><![CDATA[PIÑON, FIJO, nene, deja, el, chupete]]></tags>
  </track>

  <track>
    <id><![CDATA[140]]></id>
    <videotitle><![CDATA[PI&#209;ON FIJO por una ventanita]]></videotitle>
    <videocode><![CDATA[_6eqAI-H0pY]]></videocode>
    <videotype><![CDATA[youtube.com]]></videotype>
    <thumbnail><![CDATA[tp-140.jpg]]></thumbnail>
    <category><![CDATA[]]></category>
    <category_id><![CDATA[2]]></category_id>
    <description><![CDATA[Bajate el dvd en:
http://www.taringa.net/posts/downloads/2428954/Pi&#241;on-Fijo-Ratdvd.html]]></description>
    <views><![CDATA[28]]></views>
    <views><![CDATA[28]]></views>
    <date><![CDATA[2012-02-03 14:49:24]]></date>
    <duration><![CDATA[02:52]]></duration>
    <rating><![CDATA[5.00]]></rating>
    <uploader><![CDATA[admin]]></uploader>
    <uploader_id><![CDATA[79]]></uploader_id>
    <avatar><![CDATA[79_4f25862a04afa.jpg]]></avatar>
    <comments><![CDATA[2]]></comments>
    <tags><![CDATA[PIÑON, FIJO, por, una, ventanita]]></tags>
  </track>

  <track>
    <id><![CDATA[133]]></id>
    <videotitle><![CDATA[C&#211;MO TOCAR &#34;LA SILLA EL&#201;CTRICA&#34; DE BARRICADA (PARTE 1)]]></videotitle>
    <videocode><![CDATA[ofPtUW_xsuQ]]></videocode>
    <videotype><![CDATA[youtube.com]]></videotype>
    <thumbnail><![CDATA[tp-133.jpg]]></thumbnail>
    <category><![CDATA[]]></category>
    <category_id><![CDATA[3]]></category_id>
    <description><![CDATA[Este v&#237;deo tiene 2 partes, ya que era muy largo. En la primera, las explicaciones, y en la segunda, el tema completo. He elegido la versi&#243;n del disco en directo &#34;Salud y rocanrol&#34;, que se parece m&#225;s a la que hacen ahora (es un poco diferente).Salud y ca&#241;a!
Equipo:
- Gibson Les Paul Studio 93
- Fender Super Champ XD en voice 8]]></description>
    <views><![CDATA[57]]></views>
    <views><![CDATA[57]]></views>
    <date><![CDATA[2011-12-18 22:27:56]]></date>
    <duration><![CDATA[07:12]]></duration>
    <rating><![CDATA[4.50]]></rating>
    <uploader><![CDATA[murcialito]]></uploader>
    <uploader_id><![CDATA[67]]></uploader_id>
    <avatar><![CDATA[67_4f2856bc37049.jpg]]></avatar>
    <comments><![CDATA[0]]></comments>
    <tags><![CDATA[La silla eléctrica, Barricada, Salud y rocanrol, Rock]]></tags>
  </track>

  <track>
    <id><![CDATA[130]]></id>
    <videotitle><![CDATA[SIEMPRE IGUAL  *  LOS SUAVES  *  ACORDES PARA GUITARRA]]></videotitle>
    <videocode><![CDATA[iemRWowVeOc]]></videocode>
    <videotype><![CDATA[youtube.com]]></videotype>
    <thumbnail><![CDATA[tp-130.jpg]]></thumbnail>
    <category><![CDATA[]]></category>
    <category_id><![CDATA[1]]></category_id>
    <description><![CDATA[(ocho de la ma&#241;ana...)
E5(5 CUERDA)   A   F#m    B

y en el cambio:

(te arrastras al labavo...)
D   A   F#m   B]]></description>
    <views><![CDATA[55]]></views>
    <views><![CDATA[55]]></views>
    <date><![CDATA[2011-12-11 13:11:39]]></date>
    <duration><![CDATA[02:37]]></duration>
    <rating><![CDATA[4.33]]></rating>
    <uploader><![CDATA[murcialito]]></uploader>
    <uploader_id><![CDATA[67]]></uploader_id>
    <avatar><![CDATA[67_4f2856bc37049.jpg]]></avatar>
    <comments><![CDATA[2]]></comments>
    <tags><![CDATA[siempre, igual, los, suaves, suave, guitarra, heavy, acordes]]></tags>
  </track>

  <track>
    <id><![CDATA[129]]></id>
    <videotitle><![CDATA[Dolores Se Llamaba Lola de Los suaves (C&#243;mo Tocar - tutorial en castellano ) www.shigaru.com]]></videotitle>
    <videocode><![CDATA[GagtliRoV6E]]></videocode>
    <videotype><![CDATA[youtube.com]]></videotype>
    <thumbnail><![CDATA[tp-129.jpg]]></thumbnail>
    <category><![CDATA[]]></category>
    <category_id><![CDATA[3]]></category_id>
    <description><![CDATA[Aqu&#237; Rodolfo os explica c&#243;mo tocar la intro de Dolores Se Llamaba Lola de Los Suaves  -------------------------------------------------

Para cientos m&#225;s tutoriales por favor visitad  http://www.shigaru.com . --------------------------------------------------

www.shigaru.com es una comunidad nueva para amantes de la m&#250;sica, donde los conocimientos musicales son compartidos gratis con el mundo. Podeis subir explicaciones de canciones enteras, o s&#243;lo la explicaci&#243;n de un riff, o un estribillo o varias t&#233;cnicas....basicamente puedes subir tutoriales de cualquier cosa. Vuestros conocimientos m&#250;sicales ser&#225;n &#250;tiles para miles de personas por el mundo
---------------------------------------

Por favor dejad comentarios y si puedes subir una versi&#243;n mejor por favor subirla a http://www.shigaru.com. Pero please no seais ofensivos porque es muy f&#225;cil criticar. No prentendemos ser m&#250;sicos profesionales, s&#243;lo queremos...]]></description>
    <views><![CDATA[68]]></views>
    <views><![CDATA[68]]></views>
    <date><![CDATA[2011-12-10 19:47:19]]></date>
    <duration><![CDATA[02:33]]></duration>
    <rating><![CDATA[4.33]]></rating>
    <uploader><![CDATA[pichica]]></uploader>
    <uploader_id><![CDATA[63]]></uploader_id>
    <avatar><![CDATA[63_50180c4c0aea8.jpg]]></avatar>
    <comments><![CDATA[2]]></comments>
    <tags><![CDATA[tutorial, rock, español, lección, leccion, clase, aprender, tocar, sting, Dolores se llamaba lola, lesson, explanation, explicacion, teacher, how, to, play, ]]></tags>
  </track>

  <track>
    <id><![CDATA[125]]></id>
    <videotitle><![CDATA[Highway to hell, AC/DC, como tocar higway to hell]]></videotitle>
    <videocode><![CDATA[rqzSONKwZlo]]></videocode>
    <videotype><![CDATA[youtube.com]]></videotype>
    <thumbnail><![CDATA[tp-125.jpg]]></thumbnail>
    <category><![CDATA[]]></category>
    <category_id><![CDATA[3]]></category_id>
    <description><![CDATA[&#60;p&#62;http://www.virtuosso.com Aprende a tocar el solo de la famosa canci&#243;n Higway to hell de AC/DC. Los mejores cursos de guitarra en DVD los tiene Virtuosso. S&#237;guenos en Twitter: http://www.twitter.com/Virtuosso&#60;/p&#62;]]></description>
    <views><![CDATA[554]]></views>
    <views><![CDATA[554]]></views>
    <date><![CDATA[2011-12-10 18:52:23]]></date>
    <duration><![CDATA[06:52]]></duration>
    <rating><![CDATA[4.50]]></rating>
    <uploader><![CDATA[admin]]></uploader>
    <uploader_id><![CDATA[79]]></uploader_id>
    <avatar><![CDATA[79_4f25862a04afa.jpg]]></avatar>
    <comments><![CDATA[2]]></comments>
    <tags><![CDATA[highway to hell, ACDC, AC DC, como tocar higway to hell, cómo tocar higwall to hell, acdc, acdc, solos en la guitarra]]></tags>
  </track>

  <track>
    <id><![CDATA[124]]></id>
    <videotitle><![CDATA[Pin Pon es un mu&#241;eco...]]></videotitle>
    <videocode><![CDATA[B6lbqdKC5NQ]]></videocode>
    <videotype><![CDATA[youtube.com]]></videotype>
    <thumbnail><![CDATA[tp-124.jpg]]></thumbnail>
    <category><![CDATA[]]></category>
    <category_id><![CDATA[3]]></category_id>
    <description><![CDATA[rondas infantiles]]></description>
    <views><![CDATA[40]]></views>
    <views><![CDATA[40]]></views>
    <date><![CDATA[2011-12-10 18:33:44]]></date>
    <duration><![CDATA[02:27]]></duration>
    <rating><![CDATA[4.00]]></rating>
    <uploader><![CDATA[murcialito]]></uploader>
    <uploader_id><![CDATA[67]]></uploader_id>
    <avatar><![CDATA[67_4f2856bc37049.jpg]]></avatar>
    <comments><![CDATA[0]]></comments>
    <tags><![CDATA[rondas, infantiles]]></tags>
  </track>

</trackList>
</playlist>
